fcc2zim/__about__.py
fcc2zim/__init__.py
fcc2zim/__main__.py
fcc2zim/build.py
fcc2zim/challenge.py
fcc2zim/constants.py
fcc2zim/context.py
fcc2zim/entrypoint.py
fcc2zim/fetch.py
fcc2zim/prebuild.py
fcc2zim/scraper.py
fcc2zim/assets/fcc_48.png
fcc2zim/fonts/Hack-ZeroSlash/Hack-ZeroSlash-Bold.woff
fcc2zim/fonts/Hack-ZeroSlash/Hack-ZeroSlash-BoldItalic.woff
fcc2zim/fonts/Hack-ZeroSlash/Hack-ZeroSlash-Italic.woff
fcc2zim/fonts/Hack-ZeroSlash/Hack-ZeroSlash-Regular.woff
fcc2zim/fonts/lato/Lato-Black.woff
fcc2zim/fonts/lato/Lato-BlackItalic.woff
fcc2zim/fonts/lato/Lato-Bold.woff
fcc2zim/fonts/lato/Lato-BoldItalic.woff
fcc2zim/fonts/lato/Lato-Hairline.woff
fcc2zim/fonts/lato/Lato-HairlineItalic.woff
fcc2zim/fonts/lato/Lato-Italic.woff
fcc2zim/fonts/lato/Lato-Light.woff
fcc2zim/fonts/lato/Lato-LightItalic.woff
fcc2zim/fonts/lato/Lato-Regular.woff
fcc2zim/mathjax/LICENSE
fcc2zim/mathjax/README.md
fcc2zim/mathjax/es5/core.js
fcc2zim/mathjax/es5/latest.js
fcc2zim/mathjax/es5/loader.js
fcc2zim/mathjax/es5/mml-chtml.js
fcc2zim/mathjax/es5/mml-svg.js
fcc2zim/mathjax/es5/node-main.js
fcc2zim/mathjax/es5/startup.js
fcc2zim/mathjax/es5/tex-chtml-full-speech.js
fcc2zim/mathjax/es5/tex-chtml-full.js
fcc2zim/mathjax/es5/tex-chtml.js
fcc2zim/mathjax/es5/tex-mml-chtml.js
fcc2zim/mathjax/es5/tex-mml-svg.js
fcc2zim/mathjax/es5/tex-svg-full.js
fcc2zim/mathjax/es5/tex-svg.js
fcc2zim/mathjax/es5/a11y/assistive-mml.js
fcc2zim/mathjax/es5/a11y/complexity.js
fcc2zim/mathjax/es5/a11y/explorer.js
fcc2zim/mathjax/es5/a11y/semantic-enrich.js
fcc2zim/mathjax/es5/a11y/sre.js
fcc2zim/mathjax/es5/adaptors/liteDOM.js
fcc2zim/mathjax/es5/input/asciimath.js
fcc2zim/mathjax/es5/input/mml.js
fcc2zim/mathjax/es5/input/tex-base.js
fcc2zim/mathjax/es5/input/tex-full.js
fcc2zim/mathjax/es5/input/tex.js
fcc2zim/mathjax/es5/input/mml/entities.js
fcc2zim/mathjax/es5/input/mml/extensions/mml3.js
fcc2zim/mathjax/es5/input/mml/extensions/mml3.sef.json
fcc2zim/mathjax/es5/input/tex/extensions/action.js
fcc2zim-2.0.2.dist-info/METADATA
fcc2zim-2.0.2.dist-info/WHEEL
fcc2zim-2.0.2.dist-info/entry_points.txt
fcc2zim-2.0.2.dist-info/RECORD
